{
  "ident": "hariyama",
  "national_pokedex_number": 297,
  "paldea_regional_pokedex_number": 117,
  "evolution_line_ident": "makuhita",
  "evolution_line_index": 1,
  "primary_type_ident": "fighting",
  "secondary_type_ident": null,
  "height": 2.3,
  "weight": 253.8,
  "genders": ["male", "female"],
  "base_stats": {
    "hp": 144,
    "attack": 120,
    "defense": 60,
    "special_attack": 40,
    "special_defense": 60,
    "speed": 50
  },
  "ability_idents": ["thick-fat", "guts", "sheer-force"],
  "move_idents": [
    "arm-thrust",
    "belly-drum",
    "body-press",
    "body-slam",
    "brick-break",
    "brine",
    "bulk-up",
    "bulldoze",
    "bullet-punch",
    "chilling-water",
    "close-combat",
    "counter",
    "cross-chop",
    "detect",
    "dig",
    "drain-punch",
    "dynamic-punch",
    "earthquake",
    "endure",
    "facade",
    "fake-out",
    "feint",
    "fire-punch",
    "fling",
    "focus-blast",
    "focus-energy",
    "focus-punch",
    "force-palm",
    "giga-impact",
    "headlong-rush",
    "heavy-slam",
    "helping-hand",
    "hyper-beam",
    "ice-punch",
    "iron-head",
    "knock-off",
    "low-kick",
    "low-sweep",
    "metronome",
    "mud-shot",
    "mud-slap",
    "poison-jab",
    "protect",
    "rain-dance",
    "rest",
    "reversal",
    "rock-slide",
    "rock-tomb",
    "sand-attack",
    "scary-face",
    "seismic-toss",
    "sleep-talk",
    "stomping-tantrum",
    "stone-edge",
    "substitute",
    "sunny-day",
    "surf",
    "swift",
    "tackle",
    "take-down",
    "taunt",
    "tera-blast",
    "thief",
    "thunder-punch",
    "whirlwind",
    "wide-guard",
    "zen-headbutt"
  ]
}
