{
  "ident": "deerling",
  "national_pokedex_number": 585,
  "paldea_regional_pokedex_number": 190,
  "evolution_line_ident": "deerling",
  "evolution_line_index": 0,
  "formes": [
    {
      "ident": "deerling-spring",
      "primary_type_ident": "normal",
      "secondary_type_ident": "grass",
      "height": 0.6,
      "weight": 19.5,
      "genders": ["male", "female"],
      "base_stats": {
        "hp": 60,
        "attack": 60,
        "defense": 50,
        "special_attack": 40,
        "special_defense": 50,
        "speed": 75
      },
      "ability_idents": ["chlorophyll", "sap-sipper", "serene-grace"],
      "move_idents": [
        "agility",
        "baton-pass",
        "body-slam",
        "bulldoze",
        "bullet-seed",
        "charm",
        "dig",
        "double-edge",
        "double-kick",
        "endure",
        "energy-ball",
        "facade",
        "fake-tears",
        "giga-drain",
        "grass-knot",
        "grassy-terrain",
        "growl",
        "headbutt",
        "helping-hand",
        "leaf-storm",
        "leech-seed",
        "light-screen",
        "magical-leaf",
        "play-rough",
        "protect",
        "rain-dance",
        "rest",
        "sand-attack",
        "seed-bomb",
        "shadow-ball",
        "sleep-talk",
        "solar-beam",
        "substitute",
        "sunny-day",
        "synthesis",
        "tackle",
        "take-down",
        "tera-blast",
        "thunder-wave",
        "trailblaze",
        "wild-charge",
        "worry-seed",
        "zen-headbutt"
      ]
    },
    {
      "ident": "deerling-summer",
      "primary_type_ident": "normal",
      "secondary_type_ident": "grass",
      "height": 0.6,
      "weight": 19.5,
      "genders": ["male", "female"],
      "base_stats": {
        "hp": 60,
        "attack": 60,
        "defense": 50,
        "special_attack": 40,
        "special_defense": 50,
        "speed": 75
      },
      "ability_idents": ["chlorophyll", "sap-sipper", "serene-grace"],
      "move_idents": [
        "agility",
        "baton-pass",
        "body-slam",
        "bulldoze",
        "bullet-seed",
        "charm",
        "dig",
        "double-edge",
        "double-kick",
        "endure",
        "energy-ball",
        "facade",
        "fake-tears",
        "giga-drain",
        "grass-knot",
        "grassy-terrain",
        "growl",
        "headbutt",
        "helping-hand",
        "leaf-storm",
        "leech-seed",
        "light-screen",
        "magical-leaf",
        "play-rough",
        "protect",
        "rain-dance",
        "rest",
        "sand-attack",
        "seed-bomb",
        "shadow-ball",
        "sleep-talk",
        "solar-beam",
        "substitute",
        "sunny-day",
        "synthesis",
        "tackle",
        "take-down",
        "tera-blast",
        "thunder-wave",
        "trailblaze",
        "wild-charge",
        "worry-seed",
        "zen-headbutt"
      ]
    },
    {
      "ident": "deerling-autumn",
      "primary_type_ident": "normal",
      "secondary_type_ident": "grass",
      "height": 0.6,
      "weight": 19.5,
      "genders": ["male", "female"],
      "base_stats": {
        "hp": 60,
        "attack": 60,
        "defense": 50,
        "special_attack": 40,
        "special_defense": 50,
        "speed": 75
      },
      "ability_idents": ["chlorophyll", "sap-sipper", "serene-grace"],
      "move_idents": [
        "agility",
        "baton-pass",
        "body-slam",
        "bulldoze",
        "bullet-seed",
        "charm",
        "dig",
        "double-edge",
        "double-kick",
        "endure",
        "energy-ball",
        "facade",
        "fake-tears",
        "giga-drain",
        "grass-knot",
        "grassy-terrain",
        "growl",
        "headbutt",
        "helping-hand",
        "leaf-storm",
        "leech-seed",
        "light-screen",
        "magical-leaf",
        "play-rough",
        "protect",
        "rain-dance",
        "rest",
        "sand-attack",
        "seed-bomb",
        "shadow-ball",
        "sleep-talk",
        "solar-beam",
        "substitute",
        "sunny-day",
        "synthesis",
        "tackle",
        "take-down",
        "tera-blast",
        "thunder-wave",
        "trailblaze",
        "wild-charge",
        "worry-seed",
        "zen-headbutt"
      ]
    },
    {
      "ident": "deerling-winter",
      "primary_type_ident": "normal",
      "secondary_type_ident": "grass",
      "height": 0.6,
      "weight": 19.5,
      "genders": ["male", "female"],
      "base_stats": {
        "hp": 60,
        "attack": 60,
        "defense": 50,
        "special_attack": 40,
        "special_defense": 50,
        "speed": 75
      },
      "ability_idents": ["chlorophyll", "sap-sipper", "serene-grace"],
      "move_idents": [
        "agility",
        "baton-pass",
        "body-slam",
        "bulldoze",
        "bullet-seed",
        "charm",
        "dig",
        "double-edge",
        "double-kick",
        "endure",
        "energy-ball",
        "facade",
        "fake-tears",
        "giga-drain",
        "grass-knot",
        "grassy-terrain",
        "growl",
        "headbutt",
        "helping-hand",
        "leaf-storm",
        "leech-seed",
        "light-screen",
        "magical-leaf",
        "play-rough",
        "protect",
        "rain-dance",
        "rest",
        "sand-attack",
        "seed-bomb",
        "shadow-ball",
        "sleep-talk",
        "solar-beam",
        "substitute",
        "sunny-day",
        "synthesis",
        "tackle",
        "take-down",
        "tera-blast",
        "thunder-wave",
        "trailblaze",
        "wild-charge",
        "worry-seed",
        "zen-headbutt"
      ]
    }
  ]
}
