{
  "ident": "sinistea",
  "national_pokedex_number": 854,
  "paldea_regional_pokedex_number": 237,
  "evolution_line_ident": "sinistea",
  "evolution_line_index": 0,
  "primary_type_ident": "ghost",
  "secondary_type_ident": null,
  "height": 0.1,
  "weight": 0.2,
  "genders": ["genderless"],
  "base_stats": {
    "hp": 40,
    "attack": 45,
    "defense": 45,
    "special_attack": 74,
    "special_defense": 54,
    "speed": 50
  },
  "ability_idents": ["weak-armor", "cursed-body"],
  "move_idents": [
    "ally-switch",
    "aromatic-mist",
    "astonish",
    "baton-pass",
    "calm-mind",
    "confuse-ray",
    "dark-pulse",
    "endure",
    "facade",
    "foul-play",
    "giga-drain",
    "hex",
    "imprison",
    "magical-leaf",
    "mega-drain",
    "memento",
    "metronome",
    "nasty-plot",
    "night-shade",
    "phantom-force",
    "protect",
    "psybeam",
    "psychic",
    "psyshock",
    "rest",
    "shadow-ball",
    "shell-smash",
    "skill-swap",
    "sleep-talk",
    "stored-power",
    "substitute",
    "sucker-punch",
    "sweet-scent",
    "tera-blast",
    "trick",
    "trick-room",
    "will-o-wisp",
    "withdraw"
  ]
}
