{
  "ident": "gothita",
  "national_pokedex_number": 574,
  "paldea_regional_pokedex_number": 234,
  "evolution_line_ident": "gothita",
  "evolution_line_index": 0,
  "primary_type_ident": "psychic",
  "secondary_type_ident": null,
  "height": 0.4,
  "weight": 5.8,
  "genders": ["male", "female"],
  "base_stats": {
    "hp": 45,
    "attack": 30,
    "defense": 50,
    "special_attack": 55,
    "special_defense": 65,
    "speed": 45
  },
  "ability_idents": ["frisk", "competitive", "shadow-tag"],
  "move_idents": [
    "calm-mind",
    "charm",
    "confusion",
    "dark-pulse",
    "endure",
    "energy-ball",
    "facade",
    "fake-out",
    "fake-tears",
    "flatter",
    "fling",
    "foul-play",
    "future-sight",
    "grass-knot",
    "heal-pulse",
    "helping-hand",
    "hypnosis",
    "imprison",
    "light-screen",
    "magic-room",
    "mean-look",
    "mirror-coat",
    "nasty-plot",
    "play-nice",
    "pound",
    "protect",
    "psybeam",
    "psychic",
    "psychic-terrain",
    "psych-up",
    "psyshock",
    "rain-dance",
    "reflect",
    "rest",
    "rock-slide",
    "rock-tomb",
    "shadow-ball",
    "skill-swap",
    "sleep-talk",
    "stored-power",
    "substitute",
    "swift",
    "taunt",
    "tera-blast",
    "thief",
    "thunderbolt",
    "thunder-wave",
    "tickle",
    "torment",
    "trick",
    "trick-room",
    "zen-headbutt"
  ]
}
