{
  "ident": "magnemite",
  "national_pokedex_number": 81,
  "paldea_regional_pokedex_number": 209,
  "evolution_line_ident": "magnemite",
  "evolution_line_index": 0,
  "primary_type_ident": "electric",
  "secondary_type_ident": "steel",
  "height": 0.3,
  "weight": 6.0,
  "genders": ["genderless"],
  "base_stats": {
    "hp": 25,
    "attack": 35,
    "defense": 70,
    "special_attack": 95,
    "special_defense": 55,
    "speed": 45
  },
  "ability_idents": ["magnet-pull", "sturdy", "analytic"],
  "move_idents": [
    "charge-beam",
    "confuse-ray",
    "discharge",
    "eerie-impulse",
    "electric-terrain",
    "electro-ball",
    "electroweb",
    "endure",
    "explosion",
    "facade",
    "flash-cannon",
    "gyro-ball",
    "heavy-slam",
    "helping-hand",
    "iron-defense",
    "iron-head",
    "light-screen",
    "lock-on",
    "magnet-rise",
    "metal-sound",
    "protect",
    "rain-dance",
    "reflect",
    "rest",
    "sandstorm",
    "screech",
    "sleep-talk",
    "spark",
    "steel-beam",
    "substitute",
    "sunny-day",
    "supersonic",
    "swift",
    "tackle",
    "take-down",
    "tera-blast",
    "thunder",
    "thunderbolt",
    "thunder-shock",
    "thunder-wave",
    "volt-switch",
    "wild-charge",
    "zap-cannon"
  ]
}
